{
  "schema_version": 1,
  "slug": "recommended-redis-conf-settings-for-new-deployment",
  "use_case_key": "redis-config-baseline-for-new-deployment",
  "title": "Redis Baseline Config for New Deployment",
  "language": "Configuration",
  "summary": "A small redis.conf baseline with security, persistence, and logging settings for a new Redis deployment.",
  "tags": ["redis", "redis.conf", "configuration", "operations", "persistence", "security"],
  "highlights": [
    "Locks down network access",
    "Enables AOF and RDB backups",
    "Sets log and data paths"
  ],
  "repo_path": "snippets/config/recommended-redis-conf-settings-for-new-deployment",
  "entry_file": "redis.conf",
  "source_files": ["redis.conf"],
  "test_files": [],
  "dependencies": [],
  "test_environment": {
    "runtime": "Redis 7.4",
    "os": ["Linux"]
  },
  "test_type": "ManualVerification",
  "test_framework": "manual verification",
  "test_case_count": 0,
  "verification_workdir": ".",
  "verification_setup": [
    "Create the ACL file referenced by aclfile before startup.",
    "Create the data directory referenced by dir and ensure Redis can write to it.",
    "Create the parent directory of logfile and ensure Redis can write to it."
  ],
  "verification_command": "Manual verification only; see README.md for the Redis 7.4 review checklist.",
  "verification_notes": "Not executed. Directive names were selected from the official Redis 7.4 redis.conf template, but the fragment still requires environment-specific validation before use.",
  "status": "Draft"
}